{
  "hidden": [
    "Development"
  ],
  "template": {
    "inherit": {
      "github": {
        "name": "yubikey-manager",
        "branch": "main"
      }
    }
  },
  "order": [
    "Releases",
    "Release_Notes",
    "Device_Permissions",
    "Config_Reference",
    "Scripting",
    "Library_Usage",
    "API_Documentation"
  ],
  "git": [
      {
          "url": "https://github.com/Yubico/yubikey-manager.git",
	  "branch": "main",
          "files": [
              ["README.adoc", "index.adoc"]
          ]
      }
  ]
}
